anyblok_dramatiq/__init__.py
anyblok_dramatiq/actor.py
anyblok_dramatiq/broker.py
anyblok_dramatiq/config.py
anyblok_dramatiq/middleware.py
anyblok_dramatiq/release.py
anyblok_dramatiq/scripts.py
anyblok_dramatiq/bloks/__init__.py
anyblok_dramatiq/bloks/dramatiq/CODE.rst
anyblok_dramatiq/bloks/dramatiq/README.rst
anyblok_dramatiq/bloks/dramatiq/__init__.py
anyblok_dramatiq/bloks/dramatiq/message.py
anyblok_dramatiq/bloks/task/CODE.rst
anyblok_dramatiq/bloks/task/README.rst
anyblok_dramatiq/bloks/task/__init__.py
anyblok_dramatiq/bloks/task/job.py
anyblok_dramatiq/bloks/task/task.py
anyblok_dramatiq/test_bloks/__init__.py
anyblok_dramatiq/test_bloks/test_1/__init__.py
anyblok_dramatiq/test_bloks/test_1/model.py
anyblok_dramatiq/test_bloks/test_2/__init__.py
anyblok_dramatiq/test_bloks/test_2/model.py
anyblok_dramatiq/tests/__init__.py
anyblok_dramatiq/tests/test_actor.py
anyblok_dramatiq/tests/test_broker.py
anyblok_dramatiq/tests/test_configuration.py
anyblok_dramatiq/tests/test_message.py
anyblok_dramatiq/tests/test_middleware.py
anyblok_dramatiq/tests/test_task.py
anyblok_dramatiq/tests/testcase.py
anyblok_dramatiq-1.0.3.dist-info/DESCRIPTION.rst
anyblok_dramatiq-1.0.3.dist-info/LICENSE.txt
anyblok_dramatiq-1.0.3.dist-info/METADATA
anyblok_dramatiq-1.0.3.dist-info/RECORD
anyblok_dramatiq-1.0.3.dist-info/WHEEL
anyblok_dramatiq-1.0.3.dist-info/entry_points.txt
anyblok_dramatiq-1.0.3.dist-info/metadata.json
anyblok_dramatiq-1.0.3.dist-info/top_level.txt
