Metadata-Version: 2.0
Name: anyblok-dramatiq
Version: 1.0.3
Summary: test simple usecase between anyblok and dramatiq
Home-page: http://docs.anyblok-dramatiq.anyblok.org/1.0.3
Author: jssuzanne
Author-email: jssuzanne@anybox.fr
License: UNKNOWN
Keywords: dramatiq
Platform: UNKNOWN
Classifier: Development Status :: 2 - Pre-Alpha
Classifier: Intended Audience :: Developers
Classifier: Natural Language :: English
Classifier: Programming Language :: Python :: 3
Classifier: Programming Language :: Python :: 3.6
Classifier: Programming Language :: Python :: 3.7
Requires-Dist: simplejson
Requires-Dist: anyblok
Requires-Dist: dramatiq (>=0.12.0)
Provides-Extra: memcached
Requires-Dist: dramatiq[memcached]; extra == 'memcached'
Provides-Extra: rabbitmq
Requires-Dist: dramatiq[rabbitmq]; extra == 'rabbitmq'
Provides-Extra: redis
Requires-Dist: dramatiq[redis]; extra == 'redis'
Provides-Extra: watch
Requires-Dist: dramatiq[watch]; extra == 'watch'
